hashlwa7ak_pkg/__init__.py
hashlwa7ak_pkg/cli_main.py
hashlwa7ak_pkg/hashlwa7ak_core.py
hashlwa7ak_pkg/hashlwa7ak_old.py
hashlwa7ak-1.0.3.dist-info/METADATA
hashlwa7ak-1.0.3.dist-info/WHEEL
hashlwa7ak-1.0.3.dist-info/entry_points.txt
hashlwa7ak-1.0.3.dist-info/top_level.txt
hashlwa7ak-1.0.3.dist-info/RECORD
