Metadata-Version: 2.4
Name: hashlwa7ak
Version: 1.0.3
Requires-Dist: requests
Requires-Dist: paramiko
Requires-Dist: beautifulsoup4
Requires-Dist: rich
Dynamic: requires-dist
